Workbook

Sheet Summary
A1: Altcoin Perpetual Short Strategy — Trade Log Summary
A3: Strategy | B3: Short the 10 biggest 30-minute gainers each scan (fade-the-pump, short-only)
A4: Signal | B4: chg_30m — Price change %, 30 minutes
A5: Direction / Side | B5: reversion / short_only
A6: Basket size (N) | B6: 10
A7: Cost assumption | B7: 5 bps per leg (taker + slippage), applied once per trade
A8: Universe | B8: Binance USDT-margined alt perpetuals (excl. BTC/ETH), 24h volume >= $1,000,000
A9: Data window | B9: =TEXT('Period Summary'!B2,"yyyy-mm-dd")&" to "&TEXT('Period Summary'!C402,"yyyy-mm-dd")
A10: Max snapshot gap allowed | B10: 8 hours (longer gaps -- delistings/data holes -- are dropped)
A12: Total trades (fills) | B12: =COUNTA('Trade Log'!C2:C4011)
A13: Total periods (rebalances) | B13: =COUNTA('Period Summary'!A2:A402)
A14: Avg shorts per period | B14: =AVERAGE('Period Summary'!D2:D402)
A15: Period return win rate | B15: =COUNTIF('Period Summary'!E2:E402,">0")/COUNTA('Period Summary'!E2:E402)
A16: Best period return | B16: =MAX('Period Summary'!E2:E402)
A17: Worst period return | B17: =MIN('Period Summary'!E2:E402)
A18: Total return (compounded) | B18: ='Period Summary'!F402-1
A19: Max drawdown | B19: =MIN('Period Summary'!H2:H402)
A20: Periods per year (annualization) | B20: =COUNTA('Period Summary'!A2:A402)/(('Period Summary'!C402-'Period Summary'!B2))*365.25
A21: Annualized Sharpe (period returns) | B21: =AVERAGE('Period Summary'!E2:E402)/STDEV('Period Summary'!E2:E402)*SQRT(B20)
A24: Note: this replays historical BI screener snapshots with a fixed cost assumption; it is a backtest, not live execution. See ../RESULTS.md for full walk-forward validation, cost/liquidity sensitivity, and caveats (funding rate not modeled, short-squeeze risk, thin-liquidity slippage).

Sheet Trade Log
A1: Entry Time | B1: Exit Time | C1: Symbol | D1: Side | E1: Signal (chg_30m %) | F1: Entry Price | G1: Exit Price | H1: Gross Return % | I1: Cost % | J1: Net Return %
A2: 46204.311 | B2: 46204.362 | C2: MMTUSDT.P | D2: short | E2: 0.021937843 | F2: 0.1678 | G2: 0.1659 | H2: 0.011323004 | I2: 0.0005 | J2: 0.010823004
A3: 46204.311 | B3: 46204.362 | C3: BTWUSDT.P | D3: short | E3: 0.024677297 | F3: 0.05396 | G3: 0.05963 | H3: -0.10507784 | I3: 0.0005 | J3: -0.10557784
A4: 46204.311 | B4: 46204.362 | C4: MEUSDT.P | D4: short | E4: 0.025013305 | F4: 0.05772 | G4: 0.05859 | H4: -0.015072765 | I4: 0.0005 | J4: -0.015572765
A5: 46204.311 | B5: 46204.362 | C5: BASEDUSDT.P | D5: short | E5: 0.026857654 | F5: 0.1035 | G5: 0.10337 | H5: 0.0012560386 | I5: 0.0005 | J5: 0.00075603865
A6: 46204.311 | B6: 46204.362 | C6: TAIKOUSDT.P | D6: short | E6: 0.029150824 | F6: 0.081 | G6: 0.0789 | H6: 0.025925926 | I6: 0.0005 | J6: 0.025425926
A7: 46204.311 | B7: 46204.362 | C7: TACUSDT.P | D7: short | E7: 0.034879626 | F7: 0.064591 | G7: 0.063719 | H7: 0.013500333 | I7: 0.0005 | J7: 0.013000333
A8: 46204.311 | B8: 46204.362 | C8: ONGUSDT.P | D8: short | E8: 0.036949517 | F8: 0.04825 | G8: 0.04503 | H8: 0.066735751 | I8: 0.0005 | J8: 0.066235751
A9: 46204.311 | B9: 46204.362 | C9: XNYUSDT.P | D9: short | E9: 0.039739991 | F9: 0.007083 | G9: 0.005697 | H9: 0.1956798 | I9: 0.0005 | J9: 0.1951798
A10: 46204.311 | B10: 46204.362 | C10: LAUSDT.P | D10: short | E10: 0.040461461 | F10: 0.06217 | G10: 0.05906 | H10: 0.050024127 | I10: 0.0005 | J10: 0.049524127
A11: 46204.311 | B11: 46204.362 | C11: CLOUSDT.P | D11: short | E11: 0.05767648 | F11: 0.16853 | G11: 0.14453 | H11: 0.14240788 | I11: 0.0005 | J11: 0.14190788
A12: 46204.362 | B12: 46204.522 | C12: MYXUSDT.P | D12: short | E12: 0.016759777 | F12: 0.0909 | G12: 0.0917 | H12: -0.0088008801 | I12: 0.0005 | J12: -0.0093008801
A13: 46204.362 | B13: 46204.522 | C13: PLUMEUSDT.P | D13: short | E13: 0.017057569 | F13: 0.00955 | G13: 0.00972 | H13: -0.017801047 | I13: 0.0005 | J13: -0.018301047
... A4011: 46265.732 | B4011: 46265.915 | C4011: 0GUSDT.P | D4011: short | E4011: 0.024813896 | F4011: 0.2064 | G4011: 0.207 | H4011: -0.0029069767 | I4011: 0.0005 | J4011: -0.0034069767

Sheet Period Summary
A1: Period # | B1: Entry Time | C1: Exit Time | D1: # Shorts | E1: Period Return % | F1: Equity (start=1.0) | G1: Running Max | H1: Drawdown %
A2: 1 | B2: 46204.311 | C2: 46204.362 | D2: 10 | E2: =AVERAGE('Trade Log'!J2:J11) | F2: =IF(A2=1,1+E2,F1*(1+E2)) | G2: =F2 | H2: =F2/G2-1
A3: 2 | B3: 46204.362 | C3: 46204.522 | D3: 10 | E3: =AVERAGE('Trade Log'!J12:J21) | F3: =IF(A3=1,1+E3,F2*(1+E3)) | G3: =MAX(G2,F3) | H3: =F3/G3-1
A4: 3 | B4: 46204.522 | C4: 46204.615 | D4: 10 | E4: =AVERAGE('Trade Log'!J22:J31) | F4: =IF(A4=1,1+E4,F3*(1+E4)) | G4: =MAX(G3,F4) | H4: =F4/G4-1
A5: 4 | B5: 46204.615 | C5: 46204.753 | D5: 10 | E5: =AVERAGE('Trade Log'!J32:J41) | F5: =IF(A5=1,1+E5,F4*(1+E5)) | G5: =MAX(G4,F5) | H5: =F5/G5-1
A6: 5 | B6: 46204.753 | C6: 46204.867 | D6: 10 | E6: =AVERAGE('Trade Log'!J42:J51) | F6: =IF(A6=1,1+E6,F5*(1+E6)) | G6: =MAX(G5,F6) | H6: =F6/G6-1
A7: 6 | B7: 46204.867 | C7: 46204.944 | D7: 10 | E7: =AVERAGE('Trade Log'!J52:J61) | F7: =IF(A7=1,1+E7,F6*(1+E7)) | G7: =MAX(G6,F7) | H7: =F7/G7-1
A8: 7 | B8: 46204.944 | C8: 46205.269 | D8: 10 | E8: =AVERAGE('Trade Log'!J62:J71) | F8: =IF(A8=1,1+E8,F7*(1+E8)) | G8: =MAX(G7,F8) | H8: =F8/G8-1
A9: 8 | B9: 46205.269 | C9: 46205.366 | D9: 10 | E9: =AVERAGE('Trade Log'!J72:J81) | F9: =IF(A9=1,1+E9,F8*(1+E9)) | G9: =MAX(G8,F9) | H9: =F9/G9-1
A10: 9 | B10: 46205.366 | C10: 46205.503 | D10: 10 | E10: =AVERAGE('Trade Log'!J82:J91) | F10: =IF(A10=1,1+E10,F9*(1+E10)) | G10: =MAX(G9,F10) | H10: =F10/G10-1
A11: 10 | B11: 46205.503 | C11: 46205.769 | D11: 10 | E11: =AVERAGE('Trade Log'!J92:J101) | F11: =IF(A11=1,1+E11,F10*(1+E11)) | G11: =MAX(G10,F11) | H11: =F11/G11-1
A12: 11 | B12: 46205.769 | C12: 46205.881 | D12: 10 | E12: =AVERAGE('Trade Log'!J102:J111) | F12: =IF(A12=1,1+E12,F11*(1+E12)) | G12: =MAX(G11,F12) | H12: =F12/G12-1
A13: 12 | B13: 46205.881 | C13: 46205.946 | D13: 10 | E13: =AVERAGE('Trade Log'!J112:J121) | F13: =IF(A13=1,1+E13,F12*(1+E13)) | G13: =MAX(G12,F13) | H13: =F13/G13-1
A14: 13 | B14: 46205.946 | C14: 46206.265 | D14: 10 | E14: =AVERAGE('Trade Log'!J122:J131) | F14: =IF(A14=1,1+E14,F13*(1+E14)) | G14: =MAX(G13,F14) | H14: =F14/G14-1
A15: 14 | B15: 46206.265 | C15: 46206.385 | D15: 10 | E15: =AVERAGE('Trade Log'!J132:J141) | F15: =IF(A15=1,1+E15,F14*(1+E15)) | G15: =MAX(G14,F15) | H15: =F15/G15-1
A16: 15 | B16: 46206.385 | C16: 46206.502 | D16: 10 | E16: =AVERAGE('Trade Log'!J142:J151) | F16: =IF(A16=1,1+E16,F15*(1+E16)) | G16: =MAX(G15,F16) | H16: =F16/G16-1
A17: 16 | B17: 46206.502 | C17: 46206.61 | D17: 10 | E17: =AVERAGE('Trade Log'!J152:J161) | F17: =IF(A17=1,1+E17,F16*(1+E17)) | G17: =MAX(G16,F17) | H17: =F17/G17-1
A18: 17 | B18: 46206.61 | C18: 46206.74 | D18: 10 | E18: =AVERAGE('Trade Log'!J162:J171) | F18: =IF(A18=1,1+E18,F17*(1+E18)) | G18: =MAX(G17,F18) | H18: =F18/G18-1
A19: 18 | B19: 46206.74 | C19: 46206.881 | D19: 10 | E19: =AVERAGE('Trade Log'!J172:J181) | F19: =IF(A19=1,1+E19,F18*(1+E19)) | G19: =MAX(G18,F19) | H19: =F19/G19-1
A20: 19 | B20: 46206.881 | C20: 46206.957 | D20: 10 | E20: =AVERAGE('Trade Log'!J182:J191) | F20: =IF(A20=1,1+E20,F19*(1+E20)) | G20: =MAX(G19,F20) | H20: =F20/G20-1
A21: 20 | B21: 46206.957 | C21: 46207.281 | D21: 10 | E21: =AVERAGE('Trade Log'!J192:J201) | F21: =IF(A21=1,1+E21,F20*(1+E21)) | G21: =MAX(G20,F21) | H21: =F21/G21-1
A22: 21 | B22: 46207.281 | C22: 46207.354 | D22: 10 | E22: =AVERAGE('Trade Log'!J202:J211) | F22: =IF(A22=1,1+E22,F21*(1+E22)) | G22: =MAX(G21,F22) | H22: =F22/G22-1
A23: 22 | B23: 46207.354 | C23: 46207.477 | D23: 10 | E23: =AVERAGE('Trade Log'!J212:J221) | F23: =IF(A23=1,1+E23,F22*(1+E23)) | G23: =MAX(G22,F23) | H23: =F23/G23-1
A24: 23 | B24: 46207.477 | C24: 46207.613 | D24: 10 | E24: =AVERAGE('Trade Log'!J222:J231) | F24: =IF(A24=1,1+E24,F23*(1+E24)) | G24: =MAX(G23,F24) | H24: =F24/G24-1
A25: 24 | B25: 46207.613 | C25: 46207.702 | D25: 10 | E25: =AVERAGE('Trade Log'!J232:J241) | F25: =IF(A25=1,1+E25,F24*(1+E25)) | G25: =MAX(G24,F25) | H25: =F25/G25-1
A26: 25 | B26: 46207.702 | C26: 46207.864 | D26: 10 | E26: =AVERAGE('Trade Log'!J242:J251) | F26: =IF(A26=1,1+E26,F25*(1+E26)) | G26: =MAX(G25,F26) | H26: =F26/G26-1
A27: 26 | B27: 46207.864 | C27: 46207.978 | D27: 10 | E27: =AVERAGE('Trade Log'!J252:J261) | F27: =IF(A27=1,1+E27,F26*(1+E27)) | G27: =MAX(G26,F27) | H27: =F27/G27-1
A28: 27 | B28: 46207.978 | C28: 46208.285 | D28: 10 | E28: =AVERAGE('Trade Log'!J262:J271) | F28: =IF(A28=1,1+E28,F27*(1+E28)) | G28: =MAX(G27,F28) | H28: =F28/G28-1
A29: 28 | B29: 46208.285 | C29: 46208.381 | D29: 10 | E29: =AVERAGE('Trade Log'!J272:J281) | F29: =IF(A29=1,1+E29,F28*(1+E29)) | G29: =MAX(G28,F29) | H29: =F29/G29-1
A30: 29 | B30: 46208.381 | C30: 46208.489 | D30: 10 | E30: =AVERAGE('Trade Log'!J282:J291) | F30: =IF(A30=1,1+E30,F29*(1+E30)) | G30: =MAX(G29,F30) | H30: =F30/G30-1
A31: 30 | B31: 46208.489 | C31: 46208.614 | D31: 10 | E31: =AVERAGE('Trade Log'!J292:J301) | F31: =IF(A31=1,1+E31,F30*(1+E31)) | G31: =MAX(G30,F31) | H31: =F31/G31-1
A32: 31 | B32: 46208.614 | C32: 46208.738 | D32: 10 | E32: =AVERAGE('Trade Log'!J302:J311) | F32: =IF(A32=1,1+E32,F31*(1+E32)) | G32: =MAX(G31,F32) | H32: =F32/G32-1
A33: 32 | B33: 46208.738 | C33: 46208.863 | D33: 10 | E33: =AVERAGE('Trade Log'!J312:J321) | F33: =IF(A33=1,1+E33,F32*(1+E33)) | G33: =MAX(G32,F33) | H33: =F33/G33-1
A34: 33 | B34: 46208.863 | C34: 46208.954 | D34: 10 | E34: =AVERAGE('Trade Log'!J322:J331) | F34: =IF(A34=1,1+E34,F33*(1+E34)) | G34: =MAX(G33,F34) | H34: =F34/G34-1
A35: 34 | B35: 46208.954 | C35: 46209.282 | D35: 10 | E35: =AVERAGE('Trade Log'!J332:J341) | F35: =IF(A35=1,1+E35,F34*(1+E35)) | G35: =MAX(G34,F35) | H35: =F35/G35-1
A36: 35 | B36: 46209.282 | C36: 46209.426 | D36: 10 | E36: =AVERAGE('Trade Log'!J342:J351) | F36: =IF(A36=1,1+E36,F35*(1+E36)) | G36: =MAX(G35,F36) | H36: =F36/G36-1
A37: 36 | B37: 46209.426 | C37: 46209.492 | D37: 10 | E37: =AVERAGE('Trade Log'!J352:J361) | F37: =IF(A37=1,1+E37,F36*(1+E37)) | G37: =MAX(G36,F37) | H37: =F37/G37-1
A38: 37 | B38: 46209.492 | C38: 46209.664 | D38: 10 | E38: =AVERAGE('Trade Log'!J362:J371) | F38: =IF(A38=1,1+E38,F37*(1+E38)) | G38: =MAX(G37,F38) | H38: =F38/G38-1
A39: 38 | B39: 46209.664 | C39: 46209.743 | D39: 10 | E39: =AVERAGE('Trade Log'!J372:J381) | F39: =IF(A39=1,1+E39,F38*(1+E39)) | G39: =MAX(G38,F39) | H39: =F39/G39-1
A40: 39 | B40: 46209.743 | C40: 46209.859 | D40: 10 | E40: =AVERAGE('Trade Log'!J382:J391) | F40: =IF(A40=1,1+E40,F39*(1+E40)) | G40: =MAX(G39,F40) | H40: =F40/G40-1
A41: 40 | B41: 46209.859 | C41: 46209.944 | D41: 10 | E41: =AVERAGE('Trade Log'!J392:J401) | F41: =IF(A41=1,1+E41,F40*(1+E41)) | G41: =MAX(G40,F41) | H41: =F41/G41-1
A42: 41 | B42: 46209.944 | C42: 46209.988 | D42: 10 | E42: =AVERAGE('Trade Log'!J402:J411) | F42: =IF(A42=1,1+E42,F41*(1+E42)) | G42: =MAX(G41,F42) | H42: =F42/G42-1
A43: 42 | B43: 46209.988 | C43: 46210.271 | D43: 10 | E43: =AVERAGE('Trade Log'!J412:J421) | F43: =IF(A43=1,1+E43,F42*(1+E43)) | G43: =MAX(G42,F43) | H43: =F43/G43-1
A44: 43 | B44: 46210.271 | C44: 46210.37 | D44: 10 | E44: =AVERAGE('Trade Log'!J422:J431) | F44: =IF(A44=1,1+E44,F43*(1+E44)) | G44: =MAX(G43,F44) | H44: =F44/G44-1
A45: 44 | B45: 46210.37 | C45: 46210.506 | D45: 10 | E45: =AVERAGE('Trade Log'!J432:J441) | F45: =IF(A45=1,1+E45,F44*(1+E45)) | G45: =MAX(G44,F45) | H45: =F45/G45-1
A46: 45 | B46: 46210.506 | C46: 46210.615 | D46: 10 | E46: =AVERAGE('Trade Log'!J442:J451) | F46: =IF(A46=1,1+E46,F45*(1+E46)) | G46: =MAX(G45,F46) | H46: =F46/G46-1
A47: 46 | B47: 46210.615 | C47: 46210.727 | D47: 10 | E47: =AVERAGE('Trade Log'!J452:J461) | F47: =IF(A47=1,1+E47,F46*(1+E47)) | G47: =MAX(G46,F47) | H47: =F47/G47-1
A48: 47 | B48: 46210.727 | C48: 46210.904 | D48: 10 | E48: =AVERAGE('Trade Log'!J462:J471) | F48: =IF(A48=1,1+E48,F47*(1+E48)) | G48: =MAX(G47,F48) | H48: =F48/G48-1
A49: 48 | B49: 46210.904 | C49: 46210.983 | D49: 10 | E49: =AVERAGE('Trade Log'!J472:J481) | F49: =IF(A49=1,1+E49,F48*(1+E49)) | G49: =MAX(G48,F49) | H49: =F49/G49-1
A50: 49 | B50: 46210.983 | C50: 46211.271 | D50: 10 | E50: =AVERAGE('Trade Log'!J482:J491) | F50: =IF(A50=1,1+E50,F49*(1+E50)) | G50: =MAX(G49,F50) | H50: =F50/G50-1
A51: 50 | B51: 46211.271 | C51: 46211.366 | D51: 10 | E51: =AVERAGE('Trade Log'!J492:J501) | F51: =IF(A51=1,1+E51,F50*(1+E51)) | G51: =MAX(G50,F51) | H51: =F51/G51-1
A52: 51 | B52: 46211.366 | C52: 46211.492 | D52: 10 | E52: =AVERAGE('Trade Log'!J502:J511) | F52: =IF(A52=1,1+E52,F51*(1+E52)) | G52: =MAX(G51,F52) | H52: =F52/G52-1
A53: 52 | B53: 46211.492 | C53: 46211.615 | D53: 10 | E53: =AVERAGE('Trade Log'!J512:J521) | F53: =IF(A53=1,1+E53,F52*(1+E53)) | G53: =MAX(G52,F53) | H53: =F53/G53-1
A54: 53 | B54: 46211.615 | C54: 46211.743 | D54: 10 | E54: =AVERAGE('Trade Log'!J522:J531) | F54: =IF(A54=1,1+E54,F53*(1+E54)) | G54: =MAX(G53,F54) | H54: =F54/G54-1
A55: 54 | B55: 46211.743 | C55: 46211.869 | D55: 10 | E55: =AVERAGE('Trade Log'!J532:J541) | F55: =IF(A55=1,1+E55,F54*(1+E55)) | G55: =MAX(G54,F55) | H55: =F55/G55-1
A56: 55 | B56: 46211.869 | C56: 46211.945 | D56: 10 | E56: =AVERAGE('Trade Log'!J542:J551) | F56: =IF(A56=1,1+E56,F55*(1+E56)) | G56: =MAX(G55,F56) | H56: =F56/G56-1
A57: 56 | B57: 46211.945 | C57: 46212.26 | D57: 10 | E57: =AVERAGE('Trade Log'!J552:J561) | F57: =IF(A57=1,1+E57,F56*(1+E57)) | G57: =MAX(G56,F57) | H57: =F57/G57-1
A58: 57 | B58: 46212.26 | C58: 46212.367 | D58: 10 | E58: =AVERAGE('Trade Log'!J562:J571) | F58: =IF(A58=1,1+E58,F57*(1+E58)) | G58: =MAX(G57,F58) | H58: =F58/G58-1
A59: 58 | B59: 46212.367 | C59: 46212.49 | D59: 10 | E59: =AVERAGE('Trade Log'!J572:J581) | F59: =IF(A59=1,1+E59,F58*(1+E59)) | G59: =MAX(G58,F59) | H59: =F59/G59-1
A60: 59 | B60: 46212.49 | C60: 46212.635 | D60: 10 | E60: =AVERAGE('Trade Log'!J582:J591) | F60: =IF(A60=1,1+E60,F59*(1+E60)) | G60: =MAX(G59,F60) | H60: =F60/G60-1
A61: 60 | B61: 46212.635 | C61: 46212.731 | D61: 10 | E61: =AVERAGE('Trade Log'!J592:J601) | F61: =IF(A61=1,1+E61,F60*(1+E61)) | G61: =MAX(G60,F61) | H61: =F61/G61-1
A62: 61 | B62: 46212.731 | C62: 46212.865 | D62: 10 | E62: =AVERAGE('Trade Log'!J602:J611) | F62: =IF(A62=1,1+E62,F61*(1+E62)) | G62: =MAX(G61,F62) | H62: =F62/G62-1
A63: 62 | B63: 46212.865 | C63: 46212.946 | D63: 10 | E63: =AVERAGE('Trade Log'!J612:J621) | F63: =IF(A63=1,1+E63,F62*(1+E63)) | G63: =MAX(G62,F63) | H63: =F63/G63-1
A64: 63 | B64: 46212.946 | C64: 46213.274 | D64: 10 | E64: =AVERAGE('Trade Log'!J622:J631) | F64: =IF(A64=1,1+E64,F63*(1+E64)) | G64: =MAX(G63,F64) | H64: =F64/G64-1
A65: 64 | B65: 46213.274 | C65: 46213.381 | D65: 10 | E65: =AVERAGE('Trade Log'!J632:J641) | F65: =IF(A65=1,1+E65,F64*(1+E65)) | G65: =MAX(G64,F65) | H65: =F65/G65-1
A66: 65 | B66: 46213.381 | C66: 46213.503 | D66: 10 | E66: =AVERAGE('Trade Log'!J642:J651) | F66: =IF(A66=1,1+E66,F65*(1+E66)) | G66: =MAX(G65,F66) | H66: =F66/G66-1
A67: 66 | B67: 46213.503 | C67: 46213.626 | D67: 10 | E67: =AVERAGE('Trade Log'!J652:J661) | F67: =IF(A67=1,1+E67,F66*(1+E67)) | G67: =MAX(G66,F67) | H67: =F67/G67-1
A68: 67 | B68: 46213.626 | C68: 46213.838 | D68: 10 | E68: =AVERAGE('Trade Log'!J662:J671) | F68: =IF(A68=1,1+E68,F67*(1+E68)) | G68: =MAX(G67,F68) | H68: =F68/G68-1
A69: 68 | B69: 46213.838 | C69: 46213.946 | D69: 10 | E69: =AVERAGE('Trade Log'!J672:J681) | F69: =IF(A69=1,1+E69,F68*(1+E69)) | G69: =MAX(G68,F69) | H69: =F69/G69-1
A70: 69 | B70: 46213.946 | C70: 46214.274 | D70: 10 | E70: =AVERAGE('Trade Log'!J682:J691) | F70: =IF(A70=1,1+E70,F69*(1+E70)) | G70: =MAX(G69,F70) | H70: =F70/G70-1
A71: 70 | B71: 46214.274 | C71: 46214.363 | D71: 10 | E71: =AVERAGE('Trade Log'!J692:J701) | F71: =IF(A71=1,1+E71,F70*(1+E71)) | G71: =MAX(G70,F71) | H71: =F71/G71-1
A72: 71 | B72: 46214.363 | C72: 46214.49 | D72: 10 | E72: =AVERAGE('Trade Log'!J702:J711) | F72: =IF(A72=1,1+E72,F71*(1+E72)) | G72: =MAX(G71,F72) | H72: =F72/G72-1
A73: 72 | B73: 46214.49 | C73: 46214.614 | D73: 10 | E73: =AVERAGE('Trade Log'!J712:J721) | F73: =IF(A73=1,1+E73,F72*(1+E73)) | G73: =MAX(G72,F73) | H73: =F73/G73-1
A74: 73 | B74: 46214.614 | C74: 46214.656 | D74: 10 | E74: =AVERAGE('Trade Log'!J722:J731) | F74: =IF(A74=1,1+E74,F73*(1+E74)) | G74: =MAX(G73,F74) | H74: =F74/G74-1
A75: 74 | B75: 46214.656 | C75: 46214.744 | D75: 10 | E75: =AVERAGE('Trade Log'!J732:J741) | F75: =IF(A75=1,1+E75,F74*(1+E75)) | G75: =MAX(G74,F75) | H75: =F75/G75-1
A76: 75 | B76: 46214.744 | C76: 46214.866 | D76: 10 | E76: =AVERAGE('Trade Log'!J742:J751) | F76: =IF(A76=1,1+E76,F75*(1+E76)) | G76: =MAX(G75,F76) | H76: =F76/G76-1
A77: 76 | B77: 46214.866 | C77: 46214.927 | D77: 10 | E77: =AVERAGE('Trade Log'!J752:J761) | F77: =IF(A77=1,1+E77,F76*(1+E77)) | G77: =MAX(G76,F77) | H77: =F77/G77-1
A78: 77 | B78: 46215.276 | C78: 46215.357 | D78: 10 | E78: =AVERAGE('Trade Log'!J762:J771) | F78: =IF(A78=1,1+E78,F77*(1+E78)) | G78: =MAX(G77,F78) | H78: =F78/G78-1
A79: 78 | B79: 46215.357 | C79: 46215.494 | D79: 10 | E79: =AVERAGE('Trade Log'!J772:J781) | F79: =IF(A79=1,1+E79,F78*(1+E79)) | G79: =MAX(G78,F79) | H79: =F79/G79-1
A80: 79 | B80: 46215.494 | C80: 46215.616 | D80: 10 | E80: =AVERAGE('Trade Log'!J782:J791) | F80: =IF(A80=1,1+E80,F79*(1+E80)) | G80: =MAX(G79,F80) | H80: =F80/G80-1
A81: 80 | B81: 46215.616 | C81: 46215.742 | D81: 10 | E81: =AVERAGE('Trade Log'!J792:J801) | F81: =IF(A81=1,1+E81,F80*(1+E81)) | G81: =MAX(G80,F81) | H81: =F81/G81-1
A82: 81 | B82: 46215.742 | C82: 46215.863 | D82: 10 | E82: =AVERAGE('Trade Log'!J802:J811) | F82: =IF(A82=1,1+E82,F81*(1+E82)) | G82: =MAX(G81,F82) | H82: =F82/G82-1
A83: 82 | B83: 46215.863 | C83: 46215.948 | D83: 10 | E83: =AVERAGE('Trade Log'!J812:J821) | F83: =IF(A83=1,1+E83,F82*(1+E83)) | G83: =MAX(G82,F83) | H83: =F83/G83-1
A84: 83 | B84: 46215.948 | C84: 46216.265 | D84: 10 | E84: =AVERAGE('Trade Log'!J822:J831) | F84: =IF(A84=1,1+E84,F83*(1+E84)) | G84: =MAX(G83,F84) | H84: =F84/G84-1
A85: 84 | B85: 46216.265 | C85: 46216.494 | D85: 10 | E85: =AVERAGE('Trade Log'!J832:J841) | F85: =IF(A85=1,1+E85,F84*(1+E85)) | G85: =MAX(G84,F85) | H85: =F85/G85-1
A86: 85 | B86: 46216.494 | C86: 46216.569 | D86: 10 | E86: =AVERAGE('Trade Log'!J842:J851) | F86: =IF(A86=1,1+E86,F85*(1+E86)) | G86: =MAX(G85,F86) | H86: =F86/G86-1
A87: 86 | B87: 46216.569 | C87: 46216.673 | D87: 10 | E87: =AVERAGE('Trade Log'!J852:J861) | F87: =IF(A87=1,1+E87,F86*(1+E87)) | G87: =MAX(G86,F87) | H87: =F87/G87-1
A88: 87 | B88: 46216.673 | C88: 46216.73 | D88: 10 | E88: =AVERAGE('Trade Log'!J862:J871) | F88: =IF(A88=1,1+E88,F87*(1+E88)) | G88: =MAX(G87,F88) | H88: =F88/G88-1
A89: 88 | B89: 46216.73 | C89: 46216.858 | D89: 10 | E89: =AVERAGE('Trade Log'!J872:J881) | F89: =IF(A89=1,1+E89,F88*(1+E89)) | G89: =MAX(G88,F89) | H89: =F89/G89-1
A90: 89 | B90: 46216.858 | C90: 46216.934 | D90: 10 | E90: =AVERAGE('Trade Log'!J882:J891) | F90: =IF(A90=1,1+E90,F89*(1+E90)) | G90: =MAX(G89,F90) | H90: =F90/G90-1
A91: 90 | B91: 46216.934 | C91: 46217.263 | D91: 10 | E91: =AVERAGE('Trade Log'!J892:J901) | F91: =IF(A91=1,1+E91,F90*(1+E91)) | G91: =MAX(G90,F91) | H91: =F91/G91-1
A92: 91 | B92: 46217.263 | C92: 46217.36 | D92: 10 | E92: =AVERAGE('Trade Log'!J902:J911) | F92: =IF(A92=1,1+E92,F91*(1+E92)) | G92: =MAX(G91,F92) | H92: =F92/G92-1
A93: 92 | B93: 46217.36 | C93: 46217.49 | D93: 10 | E93: =AVERAGE('Trade Log'!J912:J921) | F93: =IF(A93=1,1+E93,F92*(1+E93)) | G93: =MAX(G92,F93) | H93: =F93/G93-1
A94: 93 | B94: 46217.49 | C94: 46217.622 | D94: 10 | E94: =AVERAGE('Trade Log'!J922:J931) | F94: =IF(A94=1,1+E94,F93*(1+E94)) | G94: =MAX(G93,F94) | H94: =F94/G94-1
A95: 94 | B95: 46217.622 | C95: 46217.738 | D95: 10 | E95: =AVERAGE('Trade Log'!J932:J941) | F95: =IF(A95=1,1+E95,F94*(1+E95)) | G95: =MAX(G94,F95) | H95: =F95/G95-1
A96: 95 | B96: 46217.738 | C96: 46217.855 | D96: 10 | E96: =AVERAGE('Trade Log'!J942:J951) | F96: =IF(A96=1,1+E96,F95*(1+E96)) | G96: =MAX(G95,F96) | H96: =F96/G96-1
A97: 96 | B97: 46217.855 | C97: 46217.931 | D97: 10 | E97: =AVERAGE('Trade Log'!J952:J961) | F97: =IF(A97=1,1+E97,F96*(1+E97)) | G97: =MAX(G96,F97) | H97: =F97/G97-1
A98: 97 | B98: 46217.931 | C98: 46218.265 | D98: 10 | E98: =AVERAGE('Trade Log'!J962:J971) | F98: =IF(A98=1,1+E98,F97*(1+E98)) | G98: =MAX(G97,F98) | H98: =F98/G98-1
A99: 98 | B99: 46218.265 | C99: 46218.349 | D99: 10 | E99: =AVERAGE('Trade Log'!J972:J981) | F99: =IF(A99=1,1+E99,F98*(1+E99)) | G99: =MAX(G98,F99) | H99: =F99/G99-1
A100: 99 | B100: 46218.349 | C100: 46218.516 | D100: 10 | E100: =AVERAGE('Trade Log'!J982:J991) | F100: =IF(A100=1,1+E100,F99*(1+E100)) | G100: =MAX(G99,F100) | H100: =F100/G100-1
...
